{"identifier":"NINETY","chain":{"nine invites":{"content":[{"value":"and","probability":1,"count":1}],"maxCount":1,"totalCount":1},"invites and":{"content":[{"value":"i","probability":1,"count":1}],"maxCount":1,"totalCount":1},"and i":{"content":[{"value":"didn't","probability":1,"count":1}],"maxCount":1,"totalCount":1},"i didn't":{"content":[{"value":"get","probability":1,"count":1}],"maxCount":1,"totalCount":1},"didn't get":{"content":[{"value":"one","probability":1,"count":1}],"maxCount":1,"totalCount":1},"get one":{"content":[{"value":",","probability":1,"count":1}],"maxCount":1,"totalCount":1},"one ,":{"content":[{"value":"just","probability":1,"count":1}],"maxCount":1,"totalCount":1},", just":{"content":[{"value":"send","probability":1,"count":1}],"maxCount":1,"totalCount":1},"just send":{"content":[{"value":"it","probability":1,"count":1}],"maxCount":1,"totalCount":1},"send it":{"content":[{"value":"to","probability":1,"count":1}],"maxCount":1,"totalCount":1},"it to":{"content":[{"value":"my","probability":1,"count":1}],"maxCount":1,"totalCount":1},"to my":{"content":[{"value":"hotmail","probability":1,"count":1}],"maxCount":1,"totalCount":1},"my hotmail":{"content":[{"value":"!","probability":1,"count":1}],"maxCount":1,"totalCount":1}},"startKeys":["nine invites"],"endKeys":["!"]}