{"identifier":"SARA","chain":{"wow that's":{"content":[{"value":"great","probability":1,"count":1}],"maxCount":1,"totalCount":1},"that's great":{"content":[{"value":".","probability":1,"count":1}],"maxCount":1,"totalCount":1},"how much":{"content":[{"value":"did","probability":1,"count":1}],"maxCount":1,"totalCount":1},"much did":{"content":[{"value":"you","probability":1,"count":1}],"maxCount":1,"totalCount":1},"did you":{"content":[{"value":"win","probability":1,"count":1}],"maxCount":1,"totalCount":1},"you win":{"content":[{"value":"?","probability":1,"count":1}],"maxCount":1,"totalCount":1}},"startKeys":["wow that's","how much"],"endKeys":[".","?"]}